GeoTrust_Primary_CA.pem
MANIFEST.in
setup.py
./__init__.py
./cli.py
./config.py
./https.py
./local.py
./remote.py
./utils.py
bin/__dotcloud_git_ssh
bin/dotcloud
dotcloud/__init__.py
dotcloud/setup.py
dotcloud.cli.egg-info/PKG-INFO
dotcloud.cli.egg-info/SOURCES.txt
dotcloud.cli.egg-info/dependency_links.txt
dotcloud.cli.egg-info/not-zip-safe
dotcloud.cli.egg-info/top_level.txt