Metadata-Version: 1.0
Name: dotcloud.cli
Version: 0.2.7
Summary: dotCloud command-line interface client
Home-page: http://www.dotcloud.com/
Author: dotCloud Inc.
Author-email: support@dotcloud.com
License: UNKNOWN
Platform: UNKNOWN
